MANIFEST.in
README.rst
requirements.txt
setup.cfg
setup.py
examples/multi_histograms.py
pyrnkr/__init__.py
pyrnkr/rpc.py
pyrnkr.egg-info/PKG-INFO
pyrnkr.egg-info/SOURCES.txt
pyrnkr.egg-info/dependency_links.txt
pyrnkr.egg-info/top_level.txt
pyrnkr/artifacts/__init__.py
pyrnkr/artifacts/models.py
pyrnkr/formula/__init__.py
pyrnkr/formula/models.py
pyrnkr/widgets/__init__.py
pyrnkr/widgets/models.py