Metadata-Version: 1.0
Name: pyrnkr
Version: 8.0
Summary: RNKR interface for Python
Home-page: https://rnkr.io
Author: Isaac Elbaz
Author-email: isaac@rnkr.io
License: UNKNOWN
Keywords: pyrnkr,rnkr,python
Platform: UNKNOWN
